[{"fuzzyI": "sLow", "fuzzyTod": "midn", "date": "11_18_2017", "locus": "mlrf1", "I": 7.9666665395, "fact_type": "windsp"}, {"fuzzyI": "Low", "fuzzyTod": "dawn", "date": "11_18_2017", "locus": "mlrf1", "I": 4.2666667302, "fact_type": "windsp"}, {"fuzzyI": "Low", "fuzzyTod": "midd", "date": "11_18_2017", "locus": "mlrf1", "I": 5.1666666667, "fact_type": "windsp"}, {"fuzzyI": "Low", "fuzzyTod": "psun", "date": "11_18_2017", "locus": "mlrf1", "I": 4.4333333174, "fact_type": "windsp"}, {"fuzzyI": "vLow", "fuzzyTod": "suns", "date": "11_18_2017", "locus": "mlrf1", "I": 3.1999999682, "fact_type": "windsp"}, {"fuzzyI": "Low", "fuzzyTod": "morn", "date": "11_18_2017", "locus": "mlrf1", "I": 5.5999999046, "fact_type": "windsp"}, {"fuzzyI": "sLow", "fuzzyTod": "even", "date": "11_18_2017", "locus": "mlrf1", "I": 9.566666921, "fact_type": "windsp"}, {"fuzzyI": "Low", "fuzzyTod": "pdaw", "date": "11_18_2017", "locus": "mlrf1", "I": 5.1999999682, "fact_type": "windsp"}]