[{"fuzzyI": "sLow", "fuzzyTod": "midn", "date": "12_27_2009", "locus": "smkf1", "I": 8.6177107068, "fact_type": "windsp"}, {"fuzzyI": "average", "fuzzyTod": "dawn", "date": "12_27_2009", "locus": "smkf1", "I": 10.8855292813, "fact_type": "windsp"}, {"fuzzyI": "average", "fuzzyTod": "midd", "date": "12_27_2009", "locus": "smkf1", "I": 11.5334771365, "fact_type": "windsp"}, {"fuzzyI": "average", "fuzzyTod": "aftn", "date": "12_27_2009", "locus": "smkf1", "I": 10.594, "fact_type": "windsp"}, {"fuzzyI": "average", "fuzzyTod": "morn", "date": "12_27_2009", "locus": "smkf1", "I": 10.107991608, "fact_type": "windsp"}, {"fuzzyI": "sLow", "fuzzyTod": "even", "date": "12_27_2009", "locus": "smkf1", "I": 5.3779697316, "fact_type": "windsp"}, {"fuzzyI": "sLow", "fuzzyTod": "pdaw", "date": "12_27_2009", "locus": "smkf1", "I": 8.3585312249, "fact_type": "windsp"}]