[{"fuzzyI": "sLow", "fuzzyTod": "midn", "date": "12_22_1995", "locus": "mlrf1", "I": 9.265658871, "fact_type": "windsp"}, {"fuzzyI": "average", "fuzzyTod": "dawn", "date": "12_22_1995", "locus": "mlrf1", "I": 16.0691149035, "fact_type": "windsp"}, {"fuzzyI": "sLow", "fuzzyTod": "midd", "date": "12_22_1995", "locus": "mlrf1", "I": 7.3866091331, "fact_type": "windsp"}, {"fuzzyI": "Low", "fuzzyTod": "aftn", "date": "12_22_1995", "locus": "mlrf1", "I": 4.86, "fact_type": "windsp"}, {"fuzzyI": "sLow", "fuzzyTod": "morn", "date": "12_22_1995", "locus": "mlrf1", "I": 9.4600431348, "fact_type": "windsp"}, {"fuzzyI": "sLow", "fuzzyTod": "even", "date": "12_22_1995", "locus": "mlrf1", "I": 7.6457884606, "fact_type": "windsp"}, {"fuzzyI": "Low", "fuzzyTod": "pdaw", "date": "12_22_1995", "locus": "mlrf1", "I": 6.9978402964, "fact_type": "windsp"}]