[{"fuzzyI": "dLow", "fuzzyTod": "midn", "date": "10_14_2010", "locus": "mlrf1", "I": 0.5999999965, "fact_type": "windsp"}, {"fuzzyI": "dLow", "fuzzyTod": "dawn", "date": "10_14_2010", "locus": "mlrf1", "I": 1.2999999722, "fact_type": "windsp"}, {"fuzzyI": "vLow", "fuzzyTod": "midd", "date": "10_14_2010", "locus": "mlrf1", "I": 2.8999999364, "fact_type": "windsp"}, {"fuzzyI": "vLow", "fuzzyTod": "aftn", "date": "10_14_2010", "locus": "mlrf1", "I": 3.6, "fact_type": "windsp"}, {"fuzzyI": "dLow", "fuzzyTod": "morn", "date": "10_14_2010", "locus": "mlrf1", "I": 1.9333333174, "fact_type": "windsp"}, {"fuzzyI": "vLow", "fuzzyTod": "even", "date": "10_14_2010", "locus": "mlrf1", "I": 2.9000000159, "fact_type": "windsp"}, {"fuzzyI": "dLow", "fuzzyTod": "pdaw", "date": "10_14_2010", "locus": "mlrf1", "I": 0.30000001190000003, "fact_type": "windsp"}]