[{"fuzzyI": "average", "fuzzyTod": "midn", "date": "01_11_2006", "locus": "mlrf1", "I": 19.6328294974, "fact_type": "windsp"}, {"fuzzyI": "average", "fuzzyTod": "dawn", "date": "01_11_2006", "locus": "mlrf1", "I": 15.0971926573, "fact_type": "windsp"}, {"fuzzyI": "average", "fuzzyTod": "midd", "date": "01_11_2006", "locus": "mlrf1", "I": 10.107991299, "fact_type": "windsp"}, {"fuzzyI": "sLow", "fuzzyTod": "psun", "date": "01_11_2006", "locus": "mlrf1", "I": 8.4881205796, "fact_type": "windsp"}, {"fuzzyI": "average", "fuzzyTod": "morn", "date": "01_11_2006", "locus": "mlrf1", "I": 12.116630855, "fact_type": "windsp"}, {"fuzzyI": "average", "fuzzyTod": "even", "date": "01_11_2006", "locus": "mlrf1", "I": 15.2267821665, "fact_type": "windsp"}, {"fuzzyI": "average", "fuzzyTod": "pdaw", "date": "01_11_2006", "locus": "mlrf1", "I": 16.5874732495, "fact_type": "windsp"}]