[{"fuzzyI": "average", "fuzzyTod": "midn", "date": "06_14_1995", "locus": "fwyf1", "I": 18.4665226783, "fact_type": "windsp"}, {"fuzzyI": "average", "fuzzyTod": "dawn", "date": "06_14_1995", "locus": "fwyf1", "I": 12.958963283, "fact_type": "windsp"}, {"fuzzyI": "Low", "fuzzyTod": "midd", "date": "06_14_1995", "locus": "fwyf1", "I": 3.0453564024, "fact_type": "windsp"}, {"fuzzyI": "Low", "fuzzyTod": "psun", "date": "06_14_1995", "locus": "fwyf1", "I": 3.4341252777, "fact_type": "windsp"}, {"fuzzyI": "sLow", "fuzzyTod": "suns", "date": "06_14_1995", "locus": "fwyf1", "I": 6.2203024686, "fact_type": "windsp"}, {"fuzzyI": "sLow", "fuzzyTod": "morn", "date": "06_14_1995", "locus": "fwyf1", "I": 9.9136070351, "fact_type": "windsp"}, {"fuzzyI": "average", "fuzzyTod": "even", "date": "06_14_1995", "locus": "fwyf1", "I": 20.2807776616, "fact_type": "windsp"}, {"fuzzyI": "average", "fuzzyTod": "pdaw", "date": "06_14_1995", "locus": "fwyf1", "I": 16.4578831223, "fact_type": "windsp"}]