[{"fuzzyI": "average", "fuzzyTod": "midn", "date": "03_28_2008", "locus": "mlrf1", "I": 15.5507562486, "fact_type": "windsp"}, {"fuzzyI": "average", "fuzzyTod": "dawn", "date": "03_28_2008", "locus": "mlrf1", "I": 10.4319653811, "fact_type": "windsp"}, {"fuzzyI": "sLow", "fuzzyTod": "midd", "date": "03_28_2008", "locus": "mlrf1", "I": 9.9136070351, "fact_type": "windsp"}, {"fuzzyI": "average", "fuzzyTod": "aftn", "date": "03_28_2008", "locus": "mlrf1", "I": 10.821, "fact_type": "windsp"}, {"fuzzyI": "sLow", "fuzzyTod": "morn", "date": "03_28_2008", "locus": "mlrf1", "I": 8.0993520519, "fact_type": "windsp"}, {"fuzzyI": "average", "fuzzyTod": "even", "date": "03_28_2008", "locus": "mlrf1", "I": 16.2634988584, "fact_type": "windsp"}, {"fuzzyI": "average", "fuzzyTod": "pdaw", "date": "03_28_2008", "locus": "mlrf1", "I": 14.7732182663, "fact_type": "windsp"}]