[{"fuzzyI": "sLow", "fuzzyTod": "midn", "date": "03_11_1999", "locus": "sanf1", "I": 6.4146867324, "fact_type": "windsp"}, {"fuzzyI": "average", "fuzzyTod": "dawn", "date": "03_11_1999", "locus": "sanf1", "I": 11.5334771365, "fact_type": "windsp"}, {"fuzzyI": "average", "fuzzyTod": "midd", "date": "03_11_1999", "locus": "sanf1", "I": 12.1814256097, "fact_type": "windsp"}, {"fuzzyI": "sLow", "fuzzyTod": "aftn", "date": "03_11_1999", "locus": "sanf1", "I": 7.16, "fact_type": "windsp"}, {"fuzzyI": "average", "fuzzyTod": "morn", "date": "03_11_1999", "locus": "sanf1", "I": 13.6069114472, "fact_type": "windsp"}, {"fuzzyI": "sLow", "fuzzyTod": "even", "date": "03_11_1999", "locus": "sanf1", "I": 8.164146961, "fact_type": "windsp"}, {"fuzzyI": "sLow", "fuzzyTod": "pdaw", "date": "03_11_1999", "locus": "sanf1", "I": 7.84017257, "fact_type": "windsp"}]