[{"fuzzyI": "sLow", "fuzzyTod": "midn", "date": "11_29_2005", "locus": "mlrf1", "I": 8.6666666667, "fact_type": "windsp"}, {"fuzzyI": "sLow", "fuzzyTod": "dawn", "date": "11_29_2005", "locus": "mlrf1", "I": 7.8999999364, "fact_type": "windsp"}, {"fuzzyI": "sLow", "fuzzyTod": "midd", "date": "11_29_2005", "locus": "mlrf1", "I": 8.566666762, "fact_type": "windsp"}, {"fuzzyI": "vLow", "fuzzyTod": "aftn", "date": "11_29_2005", "locus": "mlrf1", "I": 3.267, "fact_type": "windsp"}, {"fuzzyI": "sLow", "fuzzyTod": "morn", "date": "11_29_2005", "locus": "mlrf1", "I": 8.1333332062, "fact_type": "windsp"}, {"fuzzyI": "sLow", "fuzzyTod": "even", "date": "11_29_2005", "locus": "mlrf1", "I": 7.4666666985, "fact_type": "windsp"}, {"fuzzyI": "sLow", "fuzzyTod": "pdaw", "date": "11_29_2005", "locus": "mlrf1", "I": 7.6666668256, "fact_type": "windsp"}]