[{"fuzzyI": "sLow", "fuzzyTod": "midn", "date": "08_16_1992", "locus": "smkf1", "I": 7.5161986424, "fact_type": "windsp"}, {"fuzzyI": "sLow", "fuzzyTod": "dawn", "date": "08_16_1992", "locus": "smkf1", "I": 5.2483801837, "fact_type": "windsp"}, {"fuzzyI": "sLow", "fuzzyTod": "midd", "date": "08_16_1992", "locus": "smkf1", "I": 6.738660969, "fact_type": "windsp"}, {"fuzzyI": "Low", "fuzzyTod": "aftn", "date": "08_16_1992", "locus": "smkf1", "I": 2.819, "fact_type": "windsp"}, {"fuzzyI": "sLow", "fuzzyTod": "morn", "date": "08_16_1992", "locus": "smkf1", "I": 8.7473000616, "fact_type": "windsp"}, {"fuzzyI": "Low", "fuzzyTod": "even", "date": "08_16_1992", "locus": "smkf1", "I": 3.8876890815, "fact_type": "windsp"}, {"fuzzyI": "average", "fuzzyTod": "pdaw", "date": "08_16_1992", "locus": "smkf1", "I": 10.950324036, "fact_type": "windsp"}]