[{"fuzzyI": "average", "fuzzyTod": "midn", "date": "09_26_1993", "locus": "fwyf1", "I": 11.0799138542, "fact_type": "windsp"}, {"fuzzyI": "average", "fuzzyTod": "dawn", "date": "09_26_1993", "locus": "fwyf1", "I": 12.6997842646, "fact_type": "windsp"}, {"fuzzyI": "sLow", "fuzzyTod": "midd", "date": "09_26_1993", "locus": "fwyf1", "I": 9.5248381984, "fact_type": "windsp"}, {"fuzzyI": "sLow", "fuzzyTod": "aftn", "date": "09_26_1993", "locus": "fwyf1", "I": 9.59, "fact_type": "windsp"}, {"fuzzyI": "average", "fuzzyTod": "morn", "date": "09_26_1993", "locus": "fwyf1", "I": 11.5982722001, "fact_type": "windsp"}, {"fuzzyI": "average", "fuzzyTod": "even", "date": "09_26_1993", "locus": "fwyf1", "I": 10.2375808082, "fact_type": "windsp"}, {"fuzzyI": "average", "fuzzyTod": "pdaw", "date": "09_26_1993", "locus": "fwyf1", "I": 14.319654366, "fact_type": "windsp"}]