[{"fuzzyI": "Low", "fuzzyTod": "midn", "date": "09_28_2002", "locus": "mlrf1", "I": 3.6285096188, "fact_type": "windsp"}, {"fuzzyI": "vLow", "fuzzyTod": "dawn", "date": "09_28_2002", "locus": "mlrf1", "I": 0.5183585246, "fact_type": "windsp"}, {"fuzzyI": "Low", "fuzzyTod": "midd", "date": "09_28_2002", "locus": "mlrf1", "I": 3.9524837395, "fact_type": "windsp"}, {"fuzzyI": "sLow", "fuzzyTod": "aftn", "date": "09_28_2002", "locus": "mlrf1", "I": 7.257, "fact_type": "windsp"}, {"fuzzyI": "sLow", "fuzzyTod": "morn", "date": "09_28_2002", "locus": "mlrf1", "I": 5.6371489818, "fact_type": "windsp"}, {"fuzzyI": "Low", "fuzzyTod": "even", "date": "09_28_2002", "locus": "mlrf1", "I": 1.7494599969, "fact_type": "windsp"}, {"fuzzyI": "Low", "fuzzyTod": "pdaw", "date": "09_28_2002", "locus": "mlrf1", "I": 3.5637149028, "fact_type": "windsp"}]