[{"fuzzyI": "sLow", "fuzzyTod": "midn", "date": "02_15_2017", "locus": "fwyf1", "I": 6.4146868869, "fact_type": "windsp"}, {"fuzzyI": "sLow", "fuzzyTod": "dawn", "date": "02_15_2017", "locus": "fwyf1", "I": 6.8034557236, "fact_type": "windsp"}, {"fuzzyI": "average", "fuzzyTod": "midd", "date": "02_15_2017", "locus": "fwyf1", "I": 20.8639313801, "fact_type": "windsp"}, {"fuzzyI": "sHigh", "fuzzyTod": "aftn", "date": "02_15_2017", "locus": "fwyf1", "I": 24.201, "fact_type": "windsp"}, {"fuzzyI": "average", "fuzzyTod": "morn", "date": "02_15_2017", "locus": "fwyf1", "I": 14.7084232027, "fact_type": "windsp"}, {"fuzzyI": "average", "fuzzyTod": "even", "date": "02_15_2017", "locus": "fwyf1", "I": 10.8207342178, "fact_type": "windsp"}, {"fuzzyI": "Low", "fuzzyTod": "pdaw", "date": "02_15_2017", "locus": "fwyf1", "I": 5.5723541499, "fact_type": "windsp"}]