[{"fuzzyI": "sHigh", "fuzzyTod": "midn", "date": "06_17_2003", "locus": "sanf1", "I": 29.2666664124, "fact_type": "seandbc"}, {"fuzzyI": "sHigh", "fuzzyTod": "dawn", "date": "06_17_2003", "locus": "sanf1", "I": 29.1000003815, "fact_type": "seandbc"}, {"fuzzyI": "average", "fuzzyTod": "midd", "date": "06_17_2003", "locus": "sanf1", "I": 28.8999996185, "fact_type": "seandbc"}, {"fuzzyI": "sHigh", "fuzzyTod": "aftn", "date": "06_17_2003", "locus": "sanf1", "I": 29.067, "fact_type": "seandbc"}, {"fuzzyI": "average", "fuzzyTod": "morn", "date": "06_17_2003", "locus": "sanf1", "I": 28.8999996185, "fact_type": "seandbc"}, {"fuzzyI": "sHigh", "fuzzyTod": "even", "date": "06_17_2003", "locus": "sanf1", "I": 29.2666664124, "fact_type": "seandbc"}, {"fuzzyI": "sHigh", "fuzzyTod": "pdaw", "date": "06_17_2003", "locus": "sanf1", "I": 29.133333842, "fact_type": "seandbc"}]