[{"fuzzyI": "Low", "fuzzyTod": "midn", "date": "08_13_1993", "locus": "mlrf1", "I": 4.2333333492, "fact_type": "windsp"}, {"fuzzyI": "vLow", "fuzzyTod": "dawn", "date": "08_13_1993", "locus": "mlrf1", "I": 3.7666665713, "fact_type": "windsp"}, {"fuzzyI": "dLow", "fuzzyTod": "midd", "date": "08_13_1993", "locus": "mlrf1", "I": 1.600000004, "fact_type": "windsp"}, {"fuzzyI": "vLow", "fuzzyTod": "aftn", "date": "08_13_1993", "locus": "mlrf1", "I": 3.217, "fact_type": "windsp"}, {"fuzzyI": "vLow", "fuzzyTod": "morn", "date": "08_13_1993", "locus": "mlrf1", "I": 3.466666619, "fact_type": "windsp"}, {"fuzzyI": "vLow", "fuzzyTod": "even", "date": "08_13_1993", "locus": "mlrf1", "I": 3.466666619, "fact_type": "windsp"}, {"fuzzyI": "vLow", "fuzzyTod": "pdaw", "date": "08_13_1993", "locus": "mlrf1", "I": 3.0, "fact_type": "windsp"}]