[{"fuzzyI": "sLow", "fuzzyTod": "midn", "date": "11_19_1990", "locus": "smkf1", "I": 7.7105832152, "fact_type": "windsp"}, {"fuzzyI": "average", "fuzzyTod": "dawn", "date": "11_19_1990", "locus": "smkf1", "I": 11.4686826909, "fact_type": "windsp"}, {"fuzzyI": "average", "fuzzyTod": "midd", "date": "11_19_1990", "locus": "smkf1", "I": 10.6263496449, "fact_type": "windsp"}, {"fuzzyI": "average", "fuzzyTod": "psun", "date": "11_19_1990", "locus": "smkf1", "I": 12.3110151189, "fact_type": "windsp"}, {"fuzzyI": "sLow", "fuzzyTod": "suns", "date": "11_19_1990", "locus": "smkf1", "I": 8.9416847889, "fact_type": "windsp"}, {"fuzzyI": "average", "fuzzyTod": "morn", "date": "11_19_1990", "locus": "smkf1", "I": 11.8574512186, "fact_type": "windsp"}, {"fuzzyI": "sLow", "fuzzyTod": "even", "date": "11_19_1990", "locus": "smkf1", "I": 7.2570193149, "fact_type": "windsp"}, {"fuzzyI": "average", "fuzzyTod": "pdaw", "date": "11_19_1990", "locus": "smkf1", "I": 10.43196569, "fact_type": "windsp"}]