[{"fuzzyI": "sLow", "fuzzyTod": "midn", "date": "10_22_2010", "locus": "smkf1", "I": 9.7840172169, "fact_type": "windsp"}, {"fuzzyI": "average", "fuzzyTod": "dawn", "date": "10_22_2010", "locus": "smkf1", "I": 11.1447086088, "fact_type": "windsp"}, {"fuzzyI": "average", "fuzzyTod": "midd", "date": "10_22_2010", "locus": "smkf1", "I": 16.0043198399, "fact_type": "windsp"}, {"fuzzyI": "average", "fuzzyTod": "aftn", "date": "10_22_2010", "locus": "smkf1", "I": 19.989, "fact_type": "windsp"}, {"fuzzyI": "average", "fuzzyTod": "morn", "date": "10_22_2010", "locus": "smkf1", "I": 14.3844491206, "fact_type": "windsp"}, {"fuzzyI": "average", "fuzzyTod": "even", "date": "10_22_2010", "locus": "smkf1", "I": 10.2375808082, "fact_type": "windsp"}, {"fuzzyI": "sLow", "fuzzyTod": "pdaw", "date": "10_22_2010", "locus": "smkf1", "I": 8.423326134, "fact_type": "windsp"}]