[{"fuzzyI": "dLow", "fuzzyTod": "midn", "date": "11_12_2006", "locus": "mlrf1", "I": 0.7000000005, "fact_type": "windsp"}, {"fuzzyI": "Low", "fuzzyTod": "dawn", "date": "11_12_2006", "locus": "mlrf1", "I": 4.9000000954, "fact_type": "windsp"}, {"fuzzyI": "dLow", "fuzzyTod": "midd", "date": "11_12_2006", "locus": "mlrf1", "I": 1.9000000159, "fact_type": "windsp"}, {"fuzzyI": "dLow", "fuzzyTod": "aftn", "date": "11_12_2006", "locus": "mlrf1", "I": 1.05, "fact_type": "windsp"}, {"fuzzyI": "Low", "fuzzyTod": "morn", "date": "11_12_2006", "locus": "mlrf1", "I": 4.066666762, "fact_type": "windsp"}, {"fuzzyI": "dLow", "fuzzyTod": "even", "date": "11_12_2006", "locus": "mlrf1", "I": 0.8666666845000001, "fact_type": "windsp"}, {"fuzzyI": "vLow", "fuzzyTod": "pdaw", "date": "11_12_2006", "locus": "mlrf1", "I": 3.1333332856, "fact_type": "windsp"}]