[{"fuzzyI": "sLow", "fuzzyTod": "midn", "date": "03_23_1992", "locus": "mlrf1", "I": 9.5666666031, "fact_type": "windsp"}, {"fuzzyI": "average", "fuzzyTod": "dawn", "date": "03_23_1992", "locus": "mlrf1", "I": 12.4333333969, "fact_type": "windsp"}, {"fuzzyI": "average", "fuzzyTod": "midd", "date": "03_23_1992", "locus": "mlrf1", "I": 10.2999998728, "fact_type": "windsp"}, {"fuzzyI": "sLow", "fuzzyTod": "aftn", "date": "03_23_1992", "locus": "mlrf1", "I": 8.75, "fact_type": "windsp"}, {"fuzzyI": "average", "fuzzyTod": "morn", "date": "03_23_1992", "locus": "mlrf1", "I": 10.2000001272, "fact_type": "windsp"}, {"fuzzyI": "sLow", "fuzzyTod": "even", "date": "03_23_1992", "locus": "mlrf1", "I": 7.3666666349, "fact_type": "windsp"}, {"fuzzyI": "average", "fuzzyTod": "pdaw", "date": "03_23_1992", "locus": "mlrf1", "I": 11.4333333969, "fact_type": "windsp"}]