[{"fuzzyI": "vLow", "fuzzyTod": "midn", "date": "09_18_1990", "locus": "mlrf1", "I": 2.9000000159, "fact_type": "windsp"}, {"fuzzyI": "dLow", "fuzzyTod": "dawn", "date": "09_18_1990", "locus": "mlrf1", "I": 1.0000000199, "fact_type": "windsp"}, {"fuzzyI": "dLow", "fuzzyTod": "midd", "date": "09_18_1990", "locus": "mlrf1", "I": 1.3333333730999999, "fact_type": "windsp"}, {"fuzzyI": "Low", "fuzzyTod": "aftn", "date": "09_18_1990", "locus": "mlrf1", "I": 4.183, "fact_type": "windsp"}, {"fuzzyI": "dLow", "fuzzyTod": "morn", "date": "09_18_1990", "locus": "mlrf1", "I": 0.4666666687, "fact_type": "windsp"}, {"fuzzyI": "vLow", "fuzzyTod": "even", "date": "09_18_1990", "locus": "mlrf1", "I": 2.0, "fact_type": "windsp"}, {"fuzzyI": "vLow", "fuzzyTod": "pdaw", "date": "09_18_1990", "locus": "mlrf1", "I": 2.0999999841, "fact_type": "windsp"}]