[{"fuzzyI": "sHigh", "fuzzyTod": "midn", "date": "01_17_1997", "locus": "smkf1", "I": 24.2980555378, "fact_type": "windsp"}, {"fuzzyI": "sHigh", "fuzzyTod": "dawn", "date": "01_17_1997", "locus": "smkf1", "I": 24.5572351742, "fact_type": "windsp"}, {"fuzzyI": "sHigh", "fuzzyTod": "midd", "date": "01_17_1997", "locus": "smkf1", "I": 21.7710585627, "fact_type": "windsp"}, {"fuzzyI": "average", "fuzzyTod": "psun", "date": "01_17_1997", "locus": "smkf1", "I": 13.6717062018, "fact_type": "windsp"}, {"fuzzyI": "sLow", "fuzzyTod": "suns", "date": "01_17_1997", "locus": "smkf1", "I": 7.2570194694, "fact_type": "windsp"}, {"fuzzyI": "sHigh", "fuzzyTod": "morn", "date": "01_17_1997", "locus": "smkf1", "I": 24.751619747, "fact_type": "windsp"}, {"fuzzyI": "average", "fuzzyTod": "even", "date": "01_17_1997", "locus": "smkf1", "I": 20.7991363165, "fact_type": "windsp"}, {"fuzzyI": "sHigh", "fuzzyTod": "pdaw", "date": "01_17_1997", "locus": "smkf1", "I": 24.3628506014, "fact_type": "windsp"}]