[{"fuzzyI": "average", "fuzzyTod": "midn", "date": "06_16_1997", "locus": "fwyf1", "I": 13.8660907747, "fact_type": "windsp"}, {"fuzzyI": "average", "fuzzyTod": "dawn", "date": "06_16_1997", "locus": "fwyf1", "I": 11.954643814, "fact_type": "windsp"}, {"fuzzyI": "sLow", "fuzzyTod": "midd", "date": "06_16_1997", "locus": "fwyf1", "I": 5.701943775, "fact_type": "windsp"}, {"fuzzyI": "sLow", "fuzzyTod": "psun", "date": "06_16_1997", "locus": "fwyf1", "I": 5.7019437364000005, "fact_type": "windsp"}, {"fuzzyI": "average", "fuzzyTod": "suns", "date": "06_16_1997", "locus": "fwyf1", "I": 12.1166305461, "fact_type": "windsp"}, {"fuzzyI": "sLow", "fuzzyTod": "morn", "date": "06_16_1997", "locus": "fwyf1", "I": 9.5896326441, "fact_type": "windsp"}, {"fuzzyI": "average", "fuzzyTod": "even", "date": "06_16_1997", "locus": "fwyf1", "I": 20.0863930887, "fact_type": "windsp"}, {"fuzzyI": "average", "fuzzyTod": "pdaw", "date": "06_16_1997", "locus": "fwyf1", "I": 11.8574515276, "fact_type": "windsp"}]