[{"fuzzyI": "vLow", "fuzzyTod": "midn", "date": "10_20_2010", "locus": "mlrf1", "I": 2.8333332936, "fact_type": "windsp"}, {"fuzzyI": "dLow", "fuzzyTod": "dawn", "date": "10_20_2010", "locus": "mlrf1", "I": 1.4999999603, "fact_type": "windsp"}, {"fuzzyI": "Low", "fuzzyTod": "midd", "date": "10_20_2010", "locus": "mlrf1", "I": 5.0333334605, "fact_type": "windsp"}, {"fuzzyI": "vLow", "fuzzyTod": "aftn", "date": "10_20_2010", "locus": "mlrf1", "I": 3.1, "fact_type": "windsp"}, {"fuzzyI": "Low", "fuzzyTod": "morn", "date": "10_20_2010", "locus": "mlrf1", "I": 4.4000000159, "fact_type": "windsp"}, {"fuzzyI": "sLow", "fuzzyTod": "even", "date": "10_20_2010", "locus": "mlrf1", "I": 7.0, "fact_type": "windsp"}, {"fuzzyI": "dLow", "fuzzyTod": "pdaw", "date": "10_20_2010", "locus": "mlrf1", "I": 1.9333333572, "fact_type": "windsp"}]