[{"fuzzyI": "sHigh", "fuzzyTod": "midn", "date": "04_18_2012", "locus": "smkf1", "I": 22.0302375812, "fact_type": "windsp"}, {"fuzzyI": "average", "fuzzyTod": "dawn", "date": "04_18_2012", "locus": "smkf1", "I": 16.2634988584, "fact_type": "windsp"}, {"fuzzyI": "average", "fuzzyTod": "midd", "date": "04_18_2012", "locus": "smkf1", "I": 13.477321938, "fact_type": "windsp"}, {"fuzzyI": "average", "fuzzyTod": "aftn", "date": "04_18_2012", "locus": "smkf1", "I": 10.95, "fact_type": "windsp"}, {"fuzzyI": "average", "fuzzyTod": "morn", "date": "04_18_2012", "locus": "smkf1", "I": 13.7365012654, "fact_type": "windsp"}, {"fuzzyI": "average", "fuzzyTod": "even", "date": "04_18_2012", "locus": "smkf1", "I": 17.688984696, "fact_type": "windsp"}, {"fuzzyI": "average", "fuzzyTod": "pdaw", "date": "04_18_2012", "locus": "smkf1", "I": 19.8272134523, "fact_type": "windsp"}]