[{"fuzzyI": "sLow", "fuzzyTod": "midn", "date": "09_24_2012", "locus": "fwyf1", "I": 9.3304536256, "fact_type": "windsp"}, {"fuzzyI": "average", "fuzzyTod": "dawn", "date": "09_24_2012", "locus": "fwyf1", "I": 10.3023758718, "fact_type": "windsp"}, {"fuzzyI": "average", "fuzzyTod": "midd", "date": "09_24_2012", "locus": "fwyf1", "I": 10.3023758718, "fact_type": "windsp"}, {"fuzzyI": "average", "fuzzyTod": "aftn", "date": "09_24_2012", "locus": "fwyf1", "I": 13.089, "fact_type": "windsp"}, {"fuzzyI": "sLow", "fuzzyTod": "morn", "date": "09_24_2012", "locus": "fwyf1", "I": 8.3585313794, "fact_type": "windsp"}, {"fuzzyI": "sLow", "fuzzyTod": "even", "date": "09_24_2012", "locus": "fwyf1", "I": 9.0712739892, "fact_type": "windsp"}, {"fuzzyI": "sLow", "fuzzyTod": "pdaw", "date": "09_24_2012", "locus": "fwyf1", "I": 6.997840142, "fact_type": "windsp"}]