[{"fuzzyI": "ulow", "fuzzyTod": "midn", "date": "12_16_2006", "locus": "smkf1", "I": 0.4399999976, "fact_type": "tide1m"}, {"fuzzyI": "ulow", "fuzzyTod": "midd", "date": "12_16_2006", "locus": "smkf1", "I": 0.7833333413, "fact_type": "tide1m"}, {"fuzzyI": "ulow", "fuzzyTod": "aftn", "date": "12_16_2006", "locus": "smkf1", "I": 1.402, "fact_type": "tide1m"}, {"fuzzyI": "ulow", "fuzzyTod": "morn", "date": "12_16_2006", "locus": "smkf1", "I": 1.0099999905, "fact_type": "tide1m"}, {"fuzzyI": "ulow", "fuzzyTod": "even", "date": "12_16_2006", "locus": "smkf1", "I": 1.3666666746, "fact_type": "tide1m"}, {"fuzzyI": "ulow", "fuzzyTod": "pdaw", "date": "12_16_2006", "locus": "smkf1", "I": 0.6133333345, "fact_type": "tide1m"}]