[{"fuzzyI": "sHigh", "fuzzyTod": "midn", "date": "07_01_2017", "locus": "fwyf1", "I": 29.7666664124, "fact_type": "seandbc"}, {"fuzzyI": "average", "fuzzyTod": "dawn", "date": "07_01_2017", "locus": "fwyf1", "I": 28.866666158, "fact_type": "seandbc"}, {"fuzzyI": "sHigh", "fuzzyTod": "midd", "date": "07_01_2017", "locus": "fwyf1", "I": 29.5000006358, "fact_type": "seandbc"}, {"fuzzyI": "sHigh", "fuzzyTod": "aftn", "date": "07_01_2017", "locus": "fwyf1", "I": 29.117, "fact_type": "seandbc"}, {"fuzzyI": "sHigh", "fuzzyTod": "morn", "date": "07_01_2017", "locus": "fwyf1", "I": 29.3666667938, "fact_type": "seandbc"}, {"fuzzyI": "sHigh", "fuzzyTod": "even", "date": "07_01_2017", "locus": "fwyf1", "I": 29.7999998728, "fact_type": "seandbc"}, {"fuzzyI": "sHigh", "fuzzyTod": "pdaw", "date": "07_01_2017", "locus": "fwyf1", "I": 29.1333332062, "fact_type": "seandbc"}]