[{"fuzzyI": "Low", "fuzzyTod": "midn", "date": "01_03_1996", "locus": "smkf1", "I": 24.3666667938, "fact_type": "seandbc"}, {"fuzzyI": "vLow", "fuzzyTod": "dawn", "date": "01_03_1996", "locus": "smkf1", "I": 23.5333334605, "fact_type": "seandbc"}, {"fuzzyI": "vLow", "fuzzyTod": "midd", "date": "01_03_1996", "locus": "smkf1", "I": 23.7999998728, "fact_type": "seandbc"}, {"fuzzyI": "vLow", "fuzzyTod": "psun", "date": "01_03_1996", "locus": "smkf1", "I": 23.0999997457, "fact_type": "seandbc"}, {"fuzzyI": "dLow", "fuzzyTod": "suns", "date": "01_03_1996", "locus": "smkf1", "I": 21.9666665395, "fact_type": "seandbc"}, {"fuzzyI": "vLow", "fuzzyTod": "morn", "date": "01_03_1996", "locus": "smkf1", "I": 23.933333079, "fact_type": "seandbc"}, {"fuzzyI": "Low", "fuzzyTod": "even", "date": "01_03_1996", "locus": "smkf1", "I": 24.433333079, "fact_type": "seandbc"}, {"fuzzyI": "vLow", "fuzzyTod": "pdaw", "date": "01_03_1996", "locus": "smkf1", "I": 23.7000001272, "fact_type": "seandbc"}]