[{"fuzzyI": "Low", "fuzzyTod": "midn", "date": "09_02_1997", "locus": "smkf1", "I": 4.3412525762, "fact_type": "windsp"}, {"fuzzyI": "sLow", "fuzzyTod": "dawn", "date": "09_02_1997", "locus": "smkf1", "I": 6.9330453873, "fact_type": "windsp"}, {"fuzzyI": "Low", "fuzzyTod": "midd", "date": "09_02_1997", "locus": "smkf1", "I": 3.6933045376, "fact_type": "windsp"}, {"fuzzyI": "sLow", "fuzzyTod": "aftn", "date": "09_02_1997", "locus": "smkf1", "I": 8.456, "fact_type": "windsp"}, {"fuzzyI": "Low", "fuzzyTod": "morn", "date": "09_02_1997", "locus": "smkf1", "I": 2.1382289108, "fact_type": "windsp"}, {"fuzzyI": "Low", "fuzzyTod": "even", "date": "09_02_1997", "locus": "smkf1", "I": 3.7580993984, "fact_type": "windsp"}, {"fuzzyI": "sLow", "fuzzyTod": "pdaw", "date": "09_02_1997", "locus": "smkf1", "I": 7.7753779698, "fact_type": "windsp"}]