[{"fuzzyI": "sLow", "fuzzyTod": "midn", "date": "04_03_2004", "locus": "mlrf1", "I": 8.3000001907, "fact_type": "windsp"}, {"fuzzyI": "Low", "fuzzyTod": "dawn", "date": "04_03_2004", "locus": "mlrf1", "I": 6.2666667302, "fact_type": "windsp"}, {"fuzzyI": "Low", "fuzzyTod": "midd", "date": "04_03_2004", "locus": "mlrf1", "I": 4.2666667302, "fact_type": "windsp"}, {"fuzzyI": "sLow", "fuzzyTod": "psun", "date": "04_03_2004", "locus": "mlrf1", "I": 7.8333333333, "fact_type": "windsp"}, {"fuzzyI": "average", "fuzzyTod": "suns", "date": "04_03_2004", "locus": "mlrf1", "I": 10.0, "fact_type": "windsp"}, {"fuzzyI": "sLow", "fuzzyTod": "morn", "date": "04_03_2004", "locus": "mlrf1", "I": 7.3666667938, "fact_type": "windsp"}, {"fuzzyI": "average", "fuzzyTod": "even", "date": "04_03_2004", "locus": "mlrf1", "I": 11.3333333333, "fact_type": "windsp"}, {"fuzzyI": "Low", "fuzzyTod": "pdaw", "date": "04_03_2004", "locus": "mlrf1", "I": 4.7666665713, "fact_type": "windsp"}]