[{"fuzzyI": "Low", "fuzzyTod": "midn", "date": "09_03_2015", "locus": "mlrf1", "I": 6.155507405, "fact_type": "windsp"}, {"fuzzyI": "vLow", "fuzzyTod": "dawn", "date": "09_03_2015", "locus": "mlrf1", "I": 2.3974081803000002, "fact_type": "windsp"}, {"fuzzyI": "dLow", "fuzzyTod": "midd", "date": "09_03_2015", "locus": "mlrf1", "I": 1.8790496606, "fact_type": "windsp"}, {"fuzzyI": "Low", "fuzzyTod": "aftn", "date": "09_03_2015", "locus": "mlrf1", "I": 4.05, "fact_type": "windsp"}, {"fuzzyI": "dLow", "fuzzyTod": "morn", "date": "09_03_2015", "locus": "mlrf1", "I": 0.5831533564, "fact_type": "windsp"}, {"fuzzyI": "Low", "fuzzyTod": "even", "date": "09_03_2015", "locus": "mlrf1", "I": 5.896328232, "fact_type": "windsp"}, {"fuzzyI": "Low", "fuzzyTod": "pdaw", "date": "09_03_2015", "locus": "mlrf1", "I": 4.0172785714, "fact_type": "windsp"}]