[{"fuzzyI": "average", "fuzzyTod": "midn", "date": "06_02_1996", "locus": "fwyf1", "I": 19.3736504789, "fact_type": "windsp"}, {"fuzzyI": "average", "fuzzyTod": "dawn", "date": "06_02_1996", "locus": "fwyf1", "I": 18.7257023148, "fact_type": "windsp"}, {"fuzzyI": "average", "fuzzyTod": "midd", "date": "06_02_1996", "locus": "fwyf1", "I": 13.1533475469, "fact_type": "windsp"}, {"fuzzyI": "average", "fuzzyTod": "aftn", "date": "06_02_1996", "locus": "fwyf1", "I": 14.028, "fact_type": "windsp"}, {"fuzzyI": "average", "fuzzyTod": "morn", "date": "06_02_1996", "locus": "fwyf1", "I": 15.4211664304, "fact_type": "windsp"}, {"fuzzyI": "sHigh", "fuzzyTod": "even", "date": "06_02_1996", "locus": "fwyf1", "I": 24.6220302378, "fact_type": "windsp"}, {"fuzzyI": "average", "fuzzyTod": "pdaw", "date": "06_02_1996", "locus": "fwyf1", "I": 19.6328294974, "fact_type": "windsp"}]