[{"fuzzyI": "sLow", "fuzzyTod": "midn", "date": "10_23_1993", "locus": "smkf1", "I": 9.6544277077, "fact_type": "windsp"}, {"fuzzyI": "average", "fuzzyTod": "dawn", "date": "10_23_1993", "locus": "smkf1", "I": 11.0151184816, "fact_type": "windsp"}, {"fuzzyI": "average", "fuzzyTod": "midd", "date": "10_23_1993", "locus": "smkf1", "I": 12.5053996917, "fact_type": "windsp"}, {"fuzzyI": "sLow", "fuzzyTod": "aftn", "date": "10_23_1993", "locus": "smkf1", "I": 8.683, "fact_type": "windsp"}, {"fuzzyI": "average", "fuzzyTod": "morn", "date": "10_23_1993", "locus": "smkf1", "I": 13.1533478559, "fact_type": "windsp"}, {"fuzzyI": "average", "fuzzyTod": "even", "date": "10_23_1993", "locus": "smkf1", "I": 12.3110151189, "fact_type": "windsp"}, {"fuzzyI": "average", "fuzzyTod": "pdaw", "date": "10_23_1993", "locus": "smkf1", "I": 11.3390928727, "fact_type": "windsp"}]