[{"fuzzyI": "vLow", "fuzzyTod": "midn", "date": "04_08_1990", "locus": "mlrf1", "I": 3.239740898, "fact_type": "windsp"}, {"fuzzyI": "vLow", "fuzzyTod": "dawn", "date": "04_08_1990", "locus": "mlrf1", "I": 2.5917926566, "fact_type": "windsp"}, {"fuzzyI": "Low", "fuzzyTod": "midd", "date": "04_08_1990", "locus": "mlrf1", "I": 5.053995804, "fact_type": "windsp"}, {"fuzzyI": "Low", "fuzzyTod": "aftn", "date": "04_08_1990", "locus": "mlrf1", "I": 6.577, "fact_type": "windsp"}, {"fuzzyI": "Low", "fuzzyTod": "morn", "date": "04_08_1990", "locus": "mlrf1", "I": 6.0259178957, "fact_type": "windsp"}, {"fuzzyI": "sLow", "fuzzyTod": "even", "date": "04_08_1990", "locus": "mlrf1", "I": 8.6177105523, "fact_type": "windsp"}, {"fuzzyI": "vLow", "fuzzyTod": "pdaw", "date": "04_08_1990", "locus": "mlrf1", "I": 3.4341252777, "fact_type": "windsp"}]