[{"fuzzyI": "Low", "fuzzyTod": "midn", "date": "05_31_2000", "locus": "fwyf1", "I": 4.6004320968, "fact_type": "windsp"}, {"fuzzyI": "average", "fuzzyTod": "dawn", "date": "05_31_2000", "locus": "fwyf1", "I": 10.3023758718, "fact_type": "windsp"}, {"fuzzyI": "average", "fuzzyTod": "midd", "date": "05_31_2000", "locus": "fwyf1", "I": 13.2829376741, "fact_type": "windsp"}, {"fuzzyI": "sLow", "fuzzyTod": "psun", "date": "05_31_2000", "locus": "fwyf1", "I": 8.2937363158, "fact_type": "windsp"}, {"fuzzyI": "average", "fuzzyTod": "suns", "date": "05_31_2000", "locus": "fwyf1", "I": 12.3758098735, "fact_type": "windsp"}, {"fuzzyI": "average", "fuzzyTod": "morn", "date": "05_31_2000", "locus": "fwyf1", "I": 15.2915766122, "fact_type": "windsp"}, {"fuzzyI": "sLow", "fuzzyTod": "even", "date": "05_31_2000", "locus": "fwyf1", "I": 7.7753778926, "fact_type": "windsp"}, {"fuzzyI": "average", "fuzzyTod": "pdaw", "date": "05_31_2000", "locus": "fwyf1", "I": 12.699783955600001, "fact_type": "windsp"}]