[{"fuzzyI": "vLow", "fuzzyTod": "midn", "date": "04_25_2006", "locus": "mlrf1", "I": 3.9000000159, "fact_type": "windsp"}, {"fuzzyI": "vLow", "fuzzyTod": "dawn", "date": "04_25_2006", "locus": "mlrf1", "I": 2.5333333810000003, "fact_type": "windsp"}, {"fuzzyI": "vLow", "fuzzyTod": "midd", "date": "04_25_2006", "locus": "mlrf1", "I": 2.5666666031, "fact_type": "windsp"}, {"fuzzyI": "vLow", "fuzzyTod": "psun", "date": "04_25_2006", "locus": "mlrf1", "I": 3.5, "fact_type": "windsp"}, {"fuzzyI": "Low", "fuzzyTod": "suns", "date": "04_25_2006", "locus": "mlrf1", "I": 4.2000001272, "fact_type": "windsp"}, {"fuzzyI": "vLow", "fuzzyTod": "morn", "date": "04_25_2006", "locus": "mlrf1", "I": 2.9000000159, "fact_type": "windsp"}, {"fuzzyI": "vLow", "fuzzyTod": "even", "date": "04_25_2006", "locus": "mlrf1", "I": 3.0333333015, "fact_type": "windsp"}, {"fuzzyI": "vLow", "fuzzyTod": "pdaw", "date": "04_25_2006", "locus": "mlrf1", "I": 3.9666666985, "fact_type": "windsp"}]