[{"fuzzyI": "average", "fuzzyTod": "midn", "date": "03_19_1993", "locus": "smkf1", "I": 15.9395250853, "fact_type": "windsp"}, {"fuzzyI": "average", "fuzzyTod": "dawn", "date": "03_19_1993", "locus": "smkf1", "I": 19.1144708425, "fact_type": "windsp"}, {"fuzzyI": "sHigh", "fuzzyTod": "midd", "date": "03_19_1993", "locus": "smkf1", "I": 22.6457885225, "fact_type": "windsp"}, {"fuzzyI": "average", "fuzzyTod": "aftn", "date": "03_19_1993", "locus": "smkf1", "I": 17.559, "fact_type": "windsp"}, {"fuzzyI": "average", "fuzzyTod": "morn", "date": "03_19_1993", "locus": "smkf1", "I": 20.0215980251, "fact_type": "windsp"}, {"fuzzyI": "average", "fuzzyTod": "even", "date": "03_19_1993", "locus": "smkf1", "I": 17.6889853139, "fact_type": "windsp"}, {"fuzzyI": "average", "fuzzyTod": "pdaw", "date": "03_19_1993", "locus": "smkf1", "I": 17.9481640234, "fact_type": "windsp"}]