[{"fuzzyI": "average", "fuzzyTod": "midn", "date": "09_05_1988", "locus": "smkf1", "I": 15.2267815486, "fact_type": "windsp"}, {"fuzzyI": "average", "fuzzyTod": "dawn", "date": "09_05_1988", "locus": "smkf1", "I": 18.5961124966, "fact_type": "windsp"}, {"fuzzyI": "average", "fuzzyTod": "midd", "date": "09_05_1988", "locus": "smkf1", "I": 19.9568029616, "fact_type": "windsp"}, {"fuzzyI": "average", "fuzzyTod": "aftn", "date": "09_05_1988", "locus": "smkf1", "I": 13.542, "fact_type": "windsp"}, {"fuzzyI": "sHigh", "fuzzyTod": "morn", "date": "09_05_1988", "locus": "smkf1", "I": 21.6414684355, "fact_type": "windsp"}, {"fuzzyI": "average", "fuzzyTod": "even", "date": "09_05_1988", "locus": "smkf1", "I": 16.5226781859, "fact_type": "windsp"}, {"fuzzyI": "average", "fuzzyTod": "pdaw", "date": "09_05_1988", "locus": "smkf1", "I": 16.6522676951, "fact_type": "windsp"}]