[{"fuzzyI": "dLow", "fuzzyTod": "midn", "date": "01_20_2011", "locus": "mlrf1", "I": 1.8666667144, "fact_type": "windsp"}, {"fuzzyI": "dLow", "fuzzyTod": "dawn", "date": "01_20_2011", "locus": "mlrf1", "I": 0.46666667110000004, "fact_type": "windsp"}, {"fuzzyI": "dLow", "fuzzyTod": "midd", "date": "01_20_2011", "locus": "mlrf1", "I": 0.3666666672, "fact_type": "windsp"}, {"fuzzyI": "dLow", "fuzzyTod": "psun", "date": "01_20_2011", "locus": "mlrf1", "I": 0.1333333378, "fact_type": "windsp"}, {"fuzzyI": "vLow", "fuzzyTod": "suns", "date": "01_20_2011", "locus": "mlrf1", "I": 3.9333333969, "fact_type": "windsp"}, {"fuzzyI": "dLow", "fuzzyTod": "morn", "date": "01_20_2011", "locus": "mlrf1", "I": 0.2666666706, "fact_type": "windsp"}, {"fuzzyI": "vLow", "fuzzyTod": "even", "date": "01_20_2011", "locus": "mlrf1", "I": 2.1000000636, "fact_type": "windsp"}, {"fuzzyI": "dLow", "fuzzyTod": "pdaw", "date": "01_20_2011", "locus": "mlrf1", "I": 0.7333333294000001, "fact_type": "windsp"}]