[{"fuzzyI": "sLow", "fuzzyTod": "midn", "date": "06_12_1994", "locus": "fwyf1", "I": 6.9330453873, "fact_type": "windsp"}, {"fuzzyI": "vLow", "fuzzyTod": "dawn", "date": "06_12_1994", "locus": "fwyf1", "I": 0.9071274385, "fact_type": "windsp"}, {"fuzzyI": "Low", "fuzzyTod": "midd", "date": "06_12_1994", "locus": "fwyf1", "I": 4.9244059858, "fact_type": "windsp"}, {"fuzzyI": "sLow", "fuzzyTod": "psun", "date": "06_12_1994", "locus": "fwyf1", "I": 6.5442765506, "fact_type": "windsp"}, {"fuzzyI": "average", "fuzzyTod": "suns", "date": "06_12_1994", "locus": "fwyf1", "I": 10.6911447085, "fact_type": "windsp"}, {"fuzzyI": "vLow", "fuzzyTod": "morn", "date": "06_12_1994", "locus": "fwyf1", "I": 1.6846652422, "fact_type": "windsp"}, {"fuzzyI": "sLow", "fuzzyTod": "even", "date": "06_12_1994", "locus": "fwyf1", "I": 8.7473003705, "fact_type": "windsp"}, {"fuzzyI": "Low", "fuzzyTod": "pdaw", "date": "06_12_1994", "locus": "fwyf1", "I": 1.8142548674, "fact_type": "windsp"}]