[{"fuzzyI": "ulow", "fuzzyTod": "midn", "date": "02_06_2014", "locus": "smkf1", "I": 0.8599999944000001, "fact_type": "tide1m"}, {"fuzzyI": "ulow", "fuzzyTod": "dawn", "date": "02_06_2014", "locus": "smkf1", "I": 0.7899999817000001, "fact_type": "tide1m"}, {"fuzzyI": "ulow", "fuzzyTod": "morn", "date": "02_06_2014", "locus": "smkf1", "I": 0.32000000770000003, "fact_type": "tide1m"}, {"fuzzyI": "ulow", "fuzzyTod": "even", "date": "02_06_2014", "locus": "smkf1", "I": 0.2033333381, "fact_type": "tide1m"}, {"fuzzyI": "ulow", "fuzzyTod": "pdaw", "date": "02_06_2014", "locus": "smkf1", "I": 1.3133333127, "fact_type": "tide1m"}]