[{"fuzzyI": "sLow", "fuzzyTod": "midn", "date": "04_21_1991", "locus": "sanf1", "I": 8.4233262885, "fact_type": "windsp"}, {"fuzzyI": "average", "fuzzyTod": "dawn", "date": "04_21_1991", "locus": "sanf1", "I": 11.9870410368, "fact_type": "windsp"}, {"fuzzyI": "sLow", "fuzzyTod": "midd", "date": "04_21_1991", "locus": "sanf1", "I": 7.0950323511, "fact_type": "windsp"}, {"fuzzyI": "sLow", "fuzzyTod": "psun", "date": "04_21_1991", "locus": "sanf1", "I": 9.5248381984, "fact_type": "windsp"}, {"fuzzyI": "average", "fuzzyTod": "suns", "date": "04_21_1991", "locus": "sanf1", "I": 11.3390925637, "fact_type": "windsp"}, {"fuzzyI": "sLow", "fuzzyTod": "morn", "date": "04_21_1991", "locus": "sanf1", "I": 9.3304536256, "fact_type": "windsp"}, {"fuzzyI": "average", "fuzzyTod": "even", "date": "04_21_1991", "locus": "sanf1", "I": 10.3671706264, "fact_type": "windsp"}, {"fuzzyI": "sLow", "fuzzyTod": "pdaw", "date": "04_21_1991", "locus": "sanf1", "I": 9.3304536256, "fact_type": "windsp"}]