[{"fuzzyI": "average", "fuzzyTod": "midn", "date": "12_10_1991", "locus": "fwyf1", "I": 24.2999992371, "fact_type": "seandbc"}, {"fuzzyI": "sLow", "fuzzyTod": "dawn", "date": "12_10_1991", "locus": "fwyf1", "I": 23.0333334605, "fact_type": "seandbc"}, {"fuzzyI": "sLow", "fuzzyTod": "midd", "date": "12_10_1991", "locus": "fwyf1", "I": 23.7000001272, "fact_type": "seandbc"}, {"fuzzyI": "sLow", "fuzzyTod": "aftn", "date": "12_10_1991", "locus": "fwyf1", "I": 23.833, "fact_type": "seandbc"}, {"fuzzyI": "sLow", "fuzzyTod": "morn", "date": "12_10_1991", "locus": "fwyf1", "I": 23.3333333333, "fact_type": "seandbc"}, {"fuzzyI": "sLow", "fuzzyTod": "even", "date": "12_10_1991", "locus": "fwyf1", "I": 23.9333337148, "fact_type": "seandbc"}, {"fuzzyI": "sLow", "fuzzyTod": "pdaw", "date": "12_10_1991", "locus": "fwyf1", "I": 23.5333334605, "fact_type": "seandbc"}]