[{"fuzzyI": "sLow", "fuzzyTod": "midn", "date": "12_10_1997", "locus": "fwyf1", "I": 8.7473002161, "fact_type": "windsp"}, {"fuzzyI": "average", "fuzzyTod": "dawn", "date": "12_10_1997", "locus": "fwyf1", "I": 15.161986794, "fact_type": "windsp"}, {"fuzzyI": "average", "fuzzyTod": "midd", "date": "12_10_1997", "locus": "fwyf1", "I": 15.3563710579, "fact_type": "windsp"}, {"fuzzyI": "average", "fuzzyTod": "aftn", "date": "12_10_1997", "locus": "fwyf1", "I": 13.089, "fact_type": "windsp"}, {"fuzzyI": "average", "fuzzyTod": "morn", "date": "12_10_1997", "locus": "fwyf1", "I": 16.5226781859, "fact_type": "windsp"}, {"fuzzyI": "sLow", "fuzzyTod": "even", "date": "12_10_1997", "locus": "fwyf1", "I": 9.9784017897, "fact_type": "windsp"}, {"fuzzyI": "average", "fuzzyTod": "pdaw", "date": "12_10_1997", "locus": "fwyf1", "I": 11.792656464, "fact_type": "windsp"}]