[{"fuzzyI": "Low", "fuzzyTod": "midn", "date": "04_10_1989", "locus": "smkf1", "I": 24.7666664124, "fact_type": "seandbc"}, {"fuzzyI": "vLow", "fuzzyTod": "dawn", "date": "04_10_1989", "locus": "smkf1", "I": 24.066666921, "fact_type": "seandbc"}, {"fuzzyI": "sLow", "fuzzyTod": "midd", "date": "04_10_1989", "locus": "smkf1", "I": 25.2999998728, "fact_type": "seandbc"}, {"fuzzyI": "average", "fuzzyTod": "aftn", "date": "04_10_1989", "locus": "smkf1", "I": 25.65, "fact_type": "seandbc"}, {"fuzzyI": "Low", "fuzzyTod": "morn", "date": "04_10_1989", "locus": "smkf1", "I": 24.8666667938, "fact_type": "seandbc"}, {"fuzzyI": "Low", "fuzzyTod": "even", "date": "04_10_1989", "locus": "smkf1", "I": 24.5000006358, "fact_type": "seandbc"}, {"fuzzyI": "Low", "fuzzyTod": "pdaw", "date": "04_10_1989", "locus": "smkf1", "I": 24.4666665395, "fact_type": "seandbc"}]