[{"fuzzyI": "average", "fuzzyTod": "midn", "date": "05_14_2008", "locus": "sanf1", "I": 13.7365012654, "fact_type": "windsp"}, {"fuzzyI": "average", "fuzzyTod": "dawn", "date": "05_14_2008", "locus": "sanf1", "I": 20.2807776616, "fact_type": "windsp"}, {"fuzzyI": "average", "fuzzyTod": "midd", "date": "05_14_2008", "locus": "sanf1", "I": 20.0215980251, "fact_type": "windsp"}, {"fuzzyI": "average", "fuzzyTod": "aftn", "date": "05_14_2008", "locus": "sanf1", "I": 18.79, "fact_type": "windsp"}, {"fuzzyI": "sHigh", "fuzzyTod": "morn", "date": "05_14_2008", "locus": "sanf1", "I": 22.6133912997, "fact_type": "windsp"}, {"fuzzyI": "sLow", "fuzzyTod": "even", "date": "05_14_2008", "locus": "sanf1", "I": 7.3218140695, "fact_type": "windsp"}, {"fuzzyI": "average", "fuzzyTod": "pdaw", "date": "05_14_2008", "locus": "sanf1", "I": 18.7904973784, "fact_type": "windsp"}]