[{"fuzzyI": "average", "fuzzyTod": "midn", "date": "02_15_2013", "locus": "smkf1", "I": 19.0496757789, "fact_type": "windsp"}, {"fuzzyI": "sLow", "fuzzyTod": "dawn", "date": "02_15_2013", "locus": "smkf1", "I": 9.7840172169, "fact_type": "windsp"}, {"fuzzyI": "sLow", "fuzzyTod": "midd", "date": "02_15_2013", "locus": "smkf1", "I": 6.1555075594, "fact_type": "windsp"}, {"fuzzyI": "sLow", "fuzzyTod": "psun", "date": "02_15_2013", "locus": "smkf1", "I": 9.784017371400001, "fact_type": "windsp"}, {"fuzzyI": "average", "fuzzyTod": "suns", "date": "02_15_2013", "locus": "smkf1", "I": 17.5593948778, "fact_type": "windsp"}, {"fuzzyI": "sLow", "fuzzyTod": "morn", "date": "02_15_2013", "locus": "smkf1", "I": 6.4146868869, "fact_type": "windsp"}, {"fuzzyI": "average", "fuzzyTod": "even", "date": "02_15_2013", "locus": "smkf1", "I": 11.1447086088, "fact_type": "windsp"}, {"fuzzyI": "average", "fuzzyTod": "pdaw", "date": "02_15_2013", "locus": "smkf1", "I": 16.5226778769, "fact_type": "windsp"}]