[{"fuzzyI": "sHigh", "fuzzyTod": "midn", "date": "09_10_2002", "locus": "smkf1", "I": 23.5205178644, "fact_type": "windsp"}, {"fuzzyI": "average", "fuzzyTod": "dawn", "date": "09_10_2002", "locus": "smkf1", "I": 10.3671706264, "fact_type": "windsp"}, {"fuzzyI": "average", "fuzzyTod": "midd", "date": "09_10_2002", "locus": "smkf1", "I": 12.3110151189, "fact_type": "windsp"}, {"fuzzyI": "average", "fuzzyTod": "aftn", "date": "09_10_2002", "locus": "smkf1", "I": 19.989, "fact_type": "windsp"}, {"fuzzyI": "average", "fuzzyTod": "morn", "date": "09_10_2002", "locus": "smkf1", "I": 12.8293734648, "fact_type": "windsp"}, {"fuzzyI": "average", "fuzzyTod": "even", "date": "09_10_2002", "locus": "smkf1", "I": 11.0799135452, "fact_type": "windsp"}, {"fuzzyI": "average", "fuzzyTod": "pdaw", "date": "09_10_2002", "locus": "smkf1", "I": 11.8574515276, "fact_type": "windsp"}]