[{"fuzzyI": "dLow", "fuzzyTod": "midn", "date": "01_29_1996", "locus": "smkf1", "I": 22.5333334605, "fact_type": "seandbc"}, {"fuzzyI": "vLow", "fuzzyTod": "dawn", "date": "01_29_1996", "locus": "smkf1", "I": 22.75, "fact_type": "seandbc"}, {"fuzzyI": "vLow", "fuzzyTod": "midd", "date": "01_29_1996", "locus": "smkf1", "I": 22.7333329519, "fact_type": "seandbc"}, {"fuzzyI": "vLow", "fuzzyTod": "aftn", "date": "01_29_1996", "locus": "smkf1", "I": 22.867, "fact_type": "seandbc"}, {"fuzzyI": "vLow", "fuzzyTod": "morn", "date": "01_29_1996", "locus": "smkf1", "I": 22.7000007629, "fact_type": "seandbc"}, {"fuzzyI": "vLow", "fuzzyTod": "even", "date": "01_29_1996", "locus": "smkf1", "I": 22.8000001907, "fact_type": "seandbc"}, {"fuzzyI": "dLow", "fuzzyTod": "pdaw", "date": "01_29_1996", "locus": "smkf1", "I": 22.633333842, "fact_type": "seandbc"}]