[{"fuzzyI": "Low", "fuzzyTod": "midn", "date": "12_25_1995", "locus": "sanf1", "I": 20.7333335876, "fact_type": "seandbc"}, {"fuzzyI": "Low", "fuzzyTod": "dawn", "date": "12_25_1995", "locus": "sanf1", "I": 20.4000002543, "fact_type": "seandbc"}, {"fuzzyI": "sLow", "fuzzyTod": "midd", "date": "12_25_1995", "locus": "sanf1", "I": 23.2999992371, "fact_type": "seandbc"}, {"fuzzyI": "sLow", "fuzzyTod": "aftn", "date": "12_25_1995", "locus": "sanf1", "I": 23.217, "fact_type": "seandbc"}, {"fuzzyI": "sLow", "fuzzyTod": "morn", "date": "12_25_1995", "locus": "sanf1", "I": 22.1666666667, "fact_type": "seandbc"}, {"fuzzyI": "Low", "fuzzyTod": "even", "date": "12_25_1995", "locus": "sanf1", "I": 20.7999998728, "fact_type": "seandbc"}, {"fuzzyI": "Low", "fuzzyTod": "pdaw", "date": "12_25_1995", "locus": "sanf1", "I": 20.5, "fact_type": "seandbc"}]