[{"fuzzyI": "average", "fuzzyTod": "midn", "date": "08_17_1993", "locus": "mlrf1", "I": 12.5701944464, "fact_type": "windsp"}, {"fuzzyI": "vLow", "fuzzyTod": "dawn", "date": "08_17_1993", "locus": "mlrf1", "I": 3.6285096575, "fact_type": "windsp"}, {"fuzzyI": "Low", "fuzzyTod": "midd", "date": "08_17_1993", "locus": "mlrf1", "I": 6.7386608917, "fact_type": "windsp"}, {"fuzzyI": "average", "fuzzyTod": "aftn", "date": "08_17_1993", "locus": "mlrf1", "I": 12.7, "fact_type": "windsp"}, {"fuzzyI": "Low", "fuzzyTod": "morn", "date": "08_17_1993", "locus": "mlrf1", "I": 6.0259178185, "fact_type": "windsp"}, {"fuzzyI": "average", "fuzzyTod": "even", "date": "08_17_1993", "locus": "mlrf1", "I": 11.0799138542, "fact_type": "windsp"}, {"fuzzyI": "Low", "fuzzyTod": "pdaw", "date": "08_17_1993", "locus": "mlrf1", "I": 4.6652268128, "fact_type": "windsp"}]