[{"fuzzyI": "sLow", "fuzzyTod": "midn", "date": "04_22_2008", "locus": "smkf1", "I": 9.4600431348, "fact_type": "windsp"}, {"fuzzyI": "sLow", "fuzzyTod": "dawn", "date": "04_22_2008", "locus": "smkf1", "I": 8.5529157977, "fact_type": "windsp"}, {"fuzzyI": "sLow", "fuzzyTod": "midd", "date": "04_22_2008", "locus": "smkf1", "I": 9.3952486892, "fact_type": "windsp"}, {"fuzzyI": "average", "fuzzyTod": "aftn", "date": "04_22_2008", "locus": "smkf1", "I": 14.903, "fact_type": "windsp"}, {"fuzzyI": "sLow", "fuzzyTod": "morn", "date": "04_22_2008", "locus": "smkf1", "I": 8.9416844799, "fact_type": "windsp"}, {"fuzzyI": "sLow", "fuzzyTod": "even", "date": "04_22_2008", "locus": "smkf1", "I": 8.8768897253, "fact_type": "windsp"}, {"fuzzyI": "average", "fuzzyTod": "pdaw", "date": "04_22_2008", "locus": "smkf1", "I": 12.3758098735, "fact_type": "windsp"}]