[{"fuzzyI": "sHigh", "fuzzyTod": "midn", "date": "09_11_1991", "locus": "mlrf1", "I": 29.6666673024, "fact_type": "seandbc"}, {"fuzzyI": "sHigh", "fuzzyTod": "dawn", "date": "09_11_1991", "locus": "mlrf1", "I": 29.2999998728, "fact_type": "seandbc"}, {"fuzzyI": "High", "fuzzyTod": "midd", "date": "09_11_1991", "locus": "mlrf1", "I": 30.2000001272, "fact_type": "seandbc"}, {"fuzzyI": "High", "fuzzyTod": "aftn", "date": "09_11_1991", "locus": "mlrf1", "I": 30.4, "fact_type": "seandbc"}, {"fuzzyI": "sHigh", "fuzzyTod": "morn", "date": "09_11_1991", "locus": "mlrf1", "I": 29.6000003815, "fact_type": "seandbc"}, {"fuzzyI": "sHigh", "fuzzyTod": "even", "date": "09_11_1991", "locus": "mlrf1", "I": 29.7666664124, "fact_type": "seandbc"}, {"fuzzyI": "sHigh", "fuzzyTod": "pdaw", "date": "09_11_1991", "locus": "mlrf1", "I": 29.566666921, "fact_type": "seandbc"}]