[{"fuzzyI": "sLow", "fuzzyTod": "midn", "date": "10_08_1999", "locus": "sanf1", "I": 9.006479389, "fact_type": "windsp"}, {"fuzzyI": "average", "fuzzyTod": "dawn", "date": "10_08_1999", "locus": "sanf1", "I": 17.17062635, "fact_type": "windsp"}, {"fuzzyI": "average", "fuzzyTod": "midd", "date": "10_08_1999", "locus": "sanf1", "I": 14.5140389388, "fact_type": "windsp"}, {"fuzzyI": "average", "fuzzyTod": "aftn", "date": "10_08_1999", "locus": "sanf1", "I": 14.644, "fact_type": "windsp"}, {"fuzzyI": "average", "fuzzyTod": "morn", "date": "10_08_1999", "locus": "sanf1", "I": 17.8185751321, "fact_type": "windsp"}, {"fuzzyI": "average", "fuzzyTod": "even", "date": "10_08_1999", "locus": "sanf1", "I": 12.7645790192, "fact_type": "windsp"}, {"fuzzyI": "average", "fuzzyTod": "pdaw", "date": "10_08_1999", "locus": "sanf1", "I": 18.401728232700002, "fact_type": "windsp"}]