[{"fuzzyI": "average", "fuzzyTod": "midn", "date": "09_09_1992", "locus": "sanf1", "I": 11.7278617094, "fact_type": "windsp"}, {"fuzzyI": "sLow", "fuzzyTod": "dawn", "date": "09_09_1992", "locus": "sanf1", "I": 4.924406063, "fact_type": "windsp"}, {"fuzzyI": "sLow", "fuzzyTod": "midd", "date": "09_09_1992", "locus": "sanf1", "I": 6.2203024686, "fact_type": "windsp"}, {"fuzzyI": "sLow", "fuzzyTod": "aftn", "date": "09_09_1992", "locus": "sanf1", "I": 5.67, "fact_type": "windsp"}, {"fuzzyI": "sLow", "fuzzyTod": "morn", "date": "09_09_1992", "locus": "sanf1", "I": 6.9978402964, "fact_type": "windsp"}, {"fuzzyI": "sLow", "fuzzyTod": "even", "date": "09_09_1992", "locus": "sanf1", "I": 9.3304536256, "fact_type": "windsp"}, {"fuzzyI": "sLow", "fuzzyTod": "pdaw", "date": "09_09_1992", "locus": "sanf1", "I": 8.8768897253, "fact_type": "windsp"}]