[{"fuzzyI": "average", "fuzzyTod": "midn", "date": "03_12_2002", "locus": "smkf1", "I": 14.9028077755, "fact_type": "windsp"}, {"fuzzyI": "average", "fuzzyTod": "dawn", "date": "03_12_2002", "locus": "smkf1", "I": 12.6997842646, "fact_type": "windsp"}, {"fuzzyI": "average", "fuzzyTod": "midd", "date": "03_12_2002", "locus": "smkf1", "I": 13.6069114472, "fact_type": "windsp"}, {"fuzzyI": "sLow", "fuzzyTod": "aftn", "date": "03_12_2002", "locus": "smkf1", "I": 8.132, "fact_type": "windsp"}, {"fuzzyI": "average", "fuzzyTod": "morn", "date": "03_12_2002", "locus": "smkf1", "I": 15.0971923483, "fact_type": "windsp"}, {"fuzzyI": "average", "fuzzyTod": "even", "date": "03_12_2002", "locus": "smkf1", "I": 15.7451402035, "fact_type": "windsp"}, {"fuzzyI": "average", "fuzzyTod": "pdaw", "date": "03_12_2002", "locus": "smkf1", "I": 13.1533478559, "fact_type": "windsp"}]