[{"fuzzyI": "average", "fuzzyTod": "midn", "date": "01_21_1990", "locus": "mlrf1", "I": 12.2462200553, "fact_type": "windsp"}, {"fuzzyI": "average", "fuzzyTod": "dawn", "date": "01_21_1990", "locus": "mlrf1", "I": 11.3390931816, "fact_type": "windsp"}, {"fuzzyI": "average", "fuzzyTod": "midd", "date": "01_21_1990", "locus": "mlrf1", "I": 10.4967601357, "fact_type": "windsp"}, {"fuzzyI": "sLow", "fuzzyTod": "aftn", "date": "01_21_1990", "locus": "mlrf1", "I": 8.521, "fact_type": "windsp"}, {"fuzzyI": "average", "fuzzyTod": "morn", "date": "01_21_1990", "locus": "mlrf1", "I": 11.9222462822, "fact_type": "windsp"}, {"fuzzyI": "average", "fuzzyTod": "even", "date": "01_21_1990", "locus": "mlrf1", "I": 10.107991299, "fact_type": "windsp"}, {"fuzzyI": "average", "fuzzyTod": "pdaw", "date": "01_21_1990", "locus": "mlrf1", "I": 12.958963283, "fact_type": "windsp"}]