[{"fuzzyI": "sLow", "fuzzyTod": "midn", "date": "03_06_1988", "locus": "smkf1", "I": 9.5248381984, "fact_type": "windsp"}, {"fuzzyI": "average", "fuzzyTod": "dawn", "date": "03_06_1988", "locus": "smkf1", "I": 13.5421166926, "fact_type": "windsp"}, {"fuzzyI": "average", "fuzzyTod": "midd", "date": "03_06_1988", "locus": "smkf1", "I": 16.3930886766, "fact_type": "windsp"}, {"fuzzyI": "average", "fuzzyTod": "aftn", "date": "03_06_1988", "locus": "smkf1", "I": 12.246, "fact_type": "windsp"}, {"fuzzyI": "average", "fuzzyTod": "morn", "date": "03_06_1988", "locus": "smkf1", "I": 17.3650112318, "fact_type": "windsp"}, {"fuzzyI": "sLow", "fuzzyTod": "even", "date": "03_06_1988", "locus": "smkf1", "I": 7.8401727245, "fact_type": "windsp"}, {"fuzzyI": "average", "fuzzyTod": "pdaw", "date": "03_06_1988", "locus": "smkf1", "I": 13.9956802839, "fact_type": "windsp"}]