[{"fuzzyI": "High", "fuzzyTod": "midn", "date": "07_31_2007", "locus": "fwyf1", "I": 29.9666665395, "fact_type": "seandbc"}, {"fuzzyI": "High", "fuzzyTod": "dawn", "date": "07_31_2007", "locus": "fwyf1", "I": 30.1666666667, "fact_type": "seandbc"}, {"fuzzyI": "sHigh", "fuzzyTod": "midd", "date": "07_31_2007", "locus": "fwyf1", "I": 29.5999997457, "fact_type": "seandbc"}, {"fuzzyI": "High", "fuzzyTod": "aftn", "date": "07_31_2007", "locus": "fwyf1", "I": 30.4, "fact_type": "seandbc"}, {"fuzzyI": "sHigh", "fuzzyTod": "morn", "date": "07_31_2007", "locus": "fwyf1", "I": 29.3999996185, "fact_type": "seandbc"}, {"fuzzyI": "High", "fuzzyTod": "even", "date": "07_31_2007", "locus": "fwyf1", "I": 30.1000003815, "fact_type": "seandbc"}, {"fuzzyI": "High", "fuzzyTod": "pdaw", "date": "07_31_2007", "locus": "fwyf1", "I": 30.1000003815, "fact_type": "seandbc"}]