[{"fuzzyI": "Low", "fuzzyTod": "midn", "date": "10_20_1991", "locus": "mlrf1", "I": 4.4333333969, "fact_type": "windsp"}, {"fuzzyI": "vLow", "fuzzyTod": "dawn", "date": "10_20_1991", "locus": "mlrf1", "I": 2.1333332856, "fact_type": "windsp"}, {"fuzzyI": "Low", "fuzzyTod": "midd", "date": "10_20_1991", "locus": "mlrf1", "I": 6.4666665395, "fact_type": "windsp"}, {"fuzzyI": "Low", "fuzzyTod": "aftn", "date": "10_20_1991", "locus": "mlrf1", "I": 4.95, "fact_type": "windsp"}, {"fuzzyI": "vLow", "fuzzyTod": "morn", "date": "10_20_1991", "locus": "mlrf1", "I": 3.3999999364, "fact_type": "windsp"}, {"fuzzyI": "Low", "fuzzyTod": "even", "date": "10_20_1991", "locus": "mlrf1", "I": 5.7666667302, "fact_type": "windsp"}, {"fuzzyI": "dLow", "fuzzyTod": "pdaw", "date": "10_20_1991", "locus": "mlrf1", "I": 1.9666666587, "fact_type": "windsp"}]