[{"fuzzyI": "average", "fuzzyTod": "midn", "date": "04_23_2011", "locus": "smkf1", "I": 17.2354214136, "fact_type": "windsp"}, {"fuzzyI": "average", "fuzzyTod": "dawn", "date": "04_23_2011", "locus": "smkf1", "I": 19.5680344338, "fact_type": "windsp"}, {"fuzzyI": "average", "fuzzyTod": "midd", "date": "04_23_2011", "locus": "smkf1", "I": 17.4298053685, "fact_type": "windsp"}, {"fuzzyI": "average", "fuzzyTod": "aftn", "date": "04_23_2011", "locus": "smkf1", "I": 14.968, "fact_type": "windsp"}, {"fuzzyI": "average", "fuzzyTod": "morn", "date": "04_23_2011", "locus": "smkf1", "I": 17.7537800685, "fact_type": "windsp"}, {"fuzzyI": "average", "fuzzyTod": "even", "date": "04_23_2011", "locus": "smkf1", "I": 17.4945998142, "fact_type": "windsp"}, {"fuzzyI": "sHigh", "fuzzyTod": "pdaw", "date": "04_23_2011", "locus": "smkf1", "I": 21.058315335, "fact_type": "windsp"}]