[{"fuzzyI": "sLow", "fuzzyTod": "midn", "date": "03_03_2005", "locus": "fwyf1", "I": 8.747300525, "fact_type": "windsp"}, {"fuzzyI": "average", "fuzzyTod": "dawn", "date": "03_03_2005", "locus": "fwyf1", "I": 10.1079914535, "fact_type": "windsp"}, {"fuzzyI": "average", "fuzzyTod": "midd", "date": "03_03_2005", "locus": "fwyf1", "I": 12.7645790192, "fact_type": "windsp"}, {"fuzzyI": "average", "fuzzyTod": "aftn", "date": "03_03_2005", "locus": "fwyf1", "I": 12.667, "fact_type": "windsp"}, {"fuzzyI": "average", "fuzzyTod": "morn", "date": "03_03_2005", "locus": "fwyf1", "I": 12.6997842646, "fact_type": "windsp"}, {"fuzzyI": "Low", "fuzzyTod": "even", "date": "03_03_2005", "locus": "fwyf1", "I": 4.1468680806, "fact_type": "windsp"}, {"fuzzyI": "sLow", "fuzzyTod": "pdaw", "date": "03_03_2005", "locus": "fwyf1", "I": 7.1922245603, "fact_type": "windsp"}]