[{"fuzzyI": "Low", "fuzzyTod": "midn", "date": "05_29_1994", "locus": "mlrf1", "I": 4.533333381, "fact_type": "windsp"}, {"fuzzyI": "vLow", "fuzzyTod": "dawn", "date": "05_29_1994", "locus": "mlrf1", "I": 3.7999999523, "fact_type": "windsp"}, {"fuzzyI": "Low", "fuzzyTod": "midd", "date": "05_29_1994", "locus": "mlrf1", "I": 4.7666666508, "fact_type": "windsp"}, {"fuzzyI": "Low", "fuzzyTod": "aftn", "date": "05_29_1994", "locus": "mlrf1", "I": 5.583, "fact_type": "windsp"}, {"fuzzyI": "Low", "fuzzyTod": "morn", "date": "05_29_1994", "locus": "mlrf1", "I": 4.1000000636, "fact_type": "windsp"}, {"fuzzyI": "Low", "fuzzyTod": "even", "date": "05_29_1994", "locus": "mlrf1", "I": 4.3333333333, "fact_type": "windsp"}, {"fuzzyI": "Low", "fuzzyTod": "pdaw", "date": "05_29_1994", "locus": "mlrf1", "I": 4.8333333333, "fact_type": "windsp"}]